{"data":[{"gid":"1206795151159635","assignee":null,"completed":false,"due_on":null,"name":"Accounts confirms time to be billed","notes":""},{"gid":"1206795151513636","assignee":null,"completed":false,"due_on":null,"name":"Assign task back to @accounts","notes":""},{"gid":"1206795151513646","assignee":null,"completed":false,"due_on":null,"name":"Accounts bills the client as per Harvest","notes":""},{"gid":"1210916926672599","assignee":{"name":"Caleb Thetard"},"completed":true,"due_on":"2025-09-02","name":"Brandt Garages 980 VDV | Final Account - QS Review","notes":"Please have a look at the Email and PO for Brandt. Our numbers don't add up with QS. There are Payments and Quotes forwarded; however, the spreadsheets and payments don't match."},{"gid":"1206795259686429","assignee":null,"completed":false,"due_on":null,"name":"Recon Procedure","notes":""},{"gid":"1206795259686439","assignee":null,"completed":false,"due_on":null,"name":"Debtors Procedure","notes":""},{"gid":"1206795259686449","assignee":null,"completed":false,"due_on":null,"name":"Recon process","notes":""},{"gid":"1212739986546413","assignee":{"name":"Caleb Thetard"},"completed":true,"due_on":"2026-04-10","name":"Quote basement nightclub","notes":""},{"gid":"1209570844602050","assignee":{"name":"Amanda"},"completed":true,"due_on":"2025-05-26","name":"Confirm Homemation was paid and rate was locked","notes":""},{"gid":"1207929280729032","assignee":{"name":"Caren Bailey"},"completed":true,"due_on":"2024-12-06","name":"Followup on payment date from Energy ETA ","notes":""},{"gid":"1206795149512055","assignee":null,"completed":false,"due_on":null,"name":"Invoice progress payment (Half of balance due, +-15%)","notes":""},{"gid":"1206795151513666","assignee":null,"completed":false,"due_on":null,"name":"Monthly Snapshot ","notes":""},{"gid":"1209909054595646","assignee":{"name":"Caren Bailey"},"completed":true,"due_on":null,"name":"Invoice Hardware of 2x Relay Modules as per wequote to Herman Berry","notes":"As Per Wequote Draft Invoice "}]}